LICENSE.md
README.md
setup.py
aquarius_time/__init__.py
aquarius_time/functions.py
aquarius_time.egg-info/PKG-INFO
aquarius_time.egg-info/SOURCES.txt
aquarius_time.egg-info/dependency_links.txt
aquarius_time.egg-info/entry_points.txt
aquarius_time.egg-info/requires.txt
aquarius_time.egg-info/top_level.txt
aquarius_time/bin/__init__.py
aquarius_time/bin/aq.py